Metadata-Version: 2.1
Name: demopackage001
Version: 0.0.1
Summary: A very basic calculator
Home-page: 
Author: Truc Vy
Author-email: toan9400@gmail.com
License: MIT
Keywords: calculator
Classifier: Development Status :: 5 - Production/Stable
Classifier: Intended Audience :: Education
Classifier: Operating System :: Microsoft :: Windows :: Windows 10
Classifier: License :: OSI Approved :: MIT License
Classifier: Programming Language :: Python :: 3
License-File: LICENSE.txt
